ScrathonPayments/__init__.py
scrathon_payments-0.2.8.dist-info/LICENSE
scrathon_payments-0.2.8.dist-info/METADATA
scrathon_payments-0.2.8.dist-info/WHEEL
scrathon_payments-0.2.8.dist-info/top_level.txt
scrathon_payments-0.2.8.dist-info/RECORD
