Metadata-Version: 2.1
Name: scrathon-payments
Version: 0.2.8
Summary: API Wrapper for ScrathonPayments
Home-page: https://github.com/Ryan-shamu-YT/ScrathonPayments
Author: Ryan_shamu
Author-email: Ryanshamu418@gmail.com
Keywords: scratch,api
Classifier: Development Status :: 4 - Beta
Classifier: Intended Audience :: Developers
Classifier: License :: OSI Approved :: MIT License
Classifier: Programming Language :: Python :: 3.6
Classifier: Programming Language :: Python :: 3.7
Classifier: Programming Language :: Python :: 3.8
Classifier: Programming Language :: Python :: 3.9
Requires-Python: >=3.6
License-File: LICENSE
Requires-Dist: requests
